ScalaGaishuRuishiLuosangLianbangLigong/README.md
ScalaGaishuRuishiLuosangLianbangLigong/__init__.py
ScalaGaishuRuishiLuosangLianbangLigong/__main__.py
ScalaGaishuRuishiLuosangLianbangLigong/file.epub
ScalaGaishuRuishiLuosangLianbangLigong/index.html
ScalaGaishuRuishiLuosangLianbangLigong/css/__init__.py
ScalaGaishuRuishiLuosangLianbangLigong/css/annotations.css
ScalaGaishuRuishiLuosangLianbangLigong/css/main.css
ScalaGaishuRuishiLuosangLianbangLigong/css/normalize.css
ScalaGaishuRuishiLuosangLianbangLigong/css/popup.css
ScalaGaishuRuishiLuosangLianbangLigong/font/__init__.py
ScalaGaishuRuishiLuosangLianbangLigong/font/fontello.eot
ScalaGaishuRuishiLuosangLianbangLigong/font/fontello.svg
ScalaGaishuRuishiLuosangLianbangLigong/font/fontello.ttf
ScalaGaishuRuishiLuosangLianbangLigong/font/fontello.woff
ScalaGaishuRuishiLuosangLianbangLigong/img/__init__.py
ScalaGaishuRuishiLuosangLianbangLigong/img/annotator-glyph-sprite.png
ScalaGaishuRuishiLuosangLianbangLigong/img/annotator-icon-sprite.png
ScalaGaishuRuishiLuosangLianbangLigong/img/apple-touch-icon.png
ScalaGaishuRuishiLuosangLianbangLigong/img/cancelfullscreen.png
ScalaGaishuRuishiLuosangLianbangLigong/img/close.png
ScalaGaishuRuishiLuosangLianbangLigong/img/fullscreen.png
ScalaGaishuRuishiLuosangLianbangLigong/img/loader.gif
ScalaGaishuRuishiLuosangLianbangLigong/img/menu-icon.png
ScalaGaishuRuishiLuosangLianbangLigong/img/save.png
ScalaGaishuRuishiLuosangLianbangLigong/img/saved.png
ScalaGaishuRuishiLuosangLianbangLigong/img/settings-s.png
ScalaGaishuRuishiLuosangLianbangLigong/img/settings.png
ScalaGaishuRuishiLuosangLianbangLigong/img/star.png
ScalaGaishuRuishiLuosangLianbangLigong/js/__init__.py
ScalaGaishuRuishiLuosangLianbangLigong/js/epub.js
ScalaGaishuRuishiLuosangLianbangLigong/js/epub.min.js
ScalaGaishuRuishiLuosangLianbangLigong/js/epub.min.map
ScalaGaishuRuishiLuosangLianbangLigong/js/hooks.min.js
ScalaGaishuRuishiLuosangLianbangLigong/js/hooks.min.map
scala_gaishu_ruishi_luosang_lianbang_ligong-2024.3.2.0.dist-info/METADATA
scala_gaishu_ruishi_luosang_lianbang_ligong-2024.3.2.0.dist-info/WHEEL
scala_gaishu_ruishi_luosang_lianbang_ligong-2024.3.2.0.dist-info/entry_points.txt
scala_gaishu_ruishi_luosang_lianbang_ligong-2024.3.2.0.dist-info/top_level.txt
scala_gaishu_ruishi_luosang_lianbang_ligong-2024.3.2.0.dist-info/RECORD
